[
    {
        "id": 1775620192892,
        "submissions": [
            {
                "qId": 1,
                "submission": "Test Answer 1"
            },
            {
                "qId": 2,
                "submission": "Test Answer 2"
            }
        ]
    },
    {
        "id": 1775620198273,
        "submissions": [
            {
                "qId": 1,
                "submission": "Test Answer 1"
            },
            {
                "qId": 2,
                "submission": "Test Answer 2"
            }
        ]
    }
]